mencryptor_dcryptor/__init__.py
mencryptor_dcryptor-0.1.0.dist-info/METADATA
mencryptor_dcryptor-0.1.0.dist-info/WHEEL
mencryptor_dcryptor-0.1.0.dist-info/top_level.txt
mencryptor_dcryptor-0.1.0.dist-info/RECORD
